{
    "_header": {
        "purchases": "Käufe",
        "labels": {
            "login": "Einloggen",
            "register": "Registrieren",
            "logout": "Ausloggen"
        },
        "start": "Start",
        "features": "Funktionen",
        "games": "Spiele",
        "pricing": "Preise",
        "partners": "Partner",
        "blog": "Blog",
        "demo": "Demo",
        "dashboard": "Dashboard",
        "contact": "Kontakt",
        "faq": "FAQ",
        "docs": "Doku",
        "admin": "Admin",
        "profile": "Profil",
        "affiliate": "Partner",
        "customers": "Communities"
    },
    "_footer": {
        "_about": {
            "supportedGames": "Unterstütze Spiele",
            "features": "Funktionen",
            "pricing": "Preise",
            "blog": "Blog",
            "demo": "Demo"
        },
        "about": "Über VyHub",
        "help": "Hilfe bekommen",
        "company": "Firma",
        "legal": "Rechtliches",
        "_help": {
            "support": "Support",
            "docs": "Dokumentation",
            "status": "Statusseite"
        },
        "_company": {
            "partners": "Partner",
            "affiliateProgramme": "Partnerprogramm",
            "affiliateProgram": "Partnerprogramm"
        },
        "_legal": {
            "about": "Über",
            "termsOfService": "AGB",
            "privacyPolicy": "Datenschutz"
        }
    },
    "_home": {
        "_faq": {
            "question3": "Gibt es eine gratis Testphase?",
            "question5": "Ich bin ein GExtension Nutzer. Kann ich meine Daten mit zu VyHub nehmen?",
            "question6": "Wo bekomme ich Hilfe?",
            "question1": "Was macht VyHub anders im Vergleich zu unserer Konkurrenz?",
            "question2": "Wie viel kostet VyHub?",
            "question4": "Kann ich meine eigene Domain nutzen?",
            "answer3": "Ja! Da wir keinen monatlichen Grundpreis verlangen, kannst du VyHub komplett gratis nutzen und testen.",
            "answer4": "Ja, du kannst deine aktuelle Domain auch mit VyHub verwenden. Dazu brauchst du nur einen CNAME record setzen.",
            "answer5": "Ja, du kannst einfach deine Daten <a target=\"_blank\" href=\"https://docs.vyhub.net/latest/guide/import/gextension/\">importieren.</a><br/><br/>",
            "answer1": "VyHub ist mehr als ein einfacher Webshop. Es ist eine all-in-one Anwendung für das Verwalten deiner Gemeinschaft mit wichtigen Funktionen wie Banns und Verwarnungen.",
            "answer2": "Das Installieren und Nutzen von VyHub ist komplett gratis. Wir berechnen nur eine kleine Gebühr auf deinen monatlichen Umsatz. So bezahlst du nur, wenn du Geld verdienst.",
            "answer6": "Bitte lies zunächst unsere <a target=\"_blank\" href=\"https://docs.vyhub.net\">Dokumentation</a> für technische Fragen. Du kannst uns über das unten stehende Kontaktformular kontaktieren."
        },
        "rightManagement": "Berechtigungskontrolle",
        "ourGoals": "Unsere Ziele",
        "andMore": "Und viel mehr..",
        "ourAmbitions": "Unsere Ambition",
        "shop": "Shop",
        "discordIntegration": "Discord Integration",
        "simple": "Einfach",
        "sections": {
            "shop": {
                "bulletPoint4": "Bedingte Angebote, Rabattcodes und mehr",
                "description": "Erstelle deinen eigenen Shop und verdiene Geld mit unserem fortschrittlichen, einfach zu bedienenden Shopsystem.",
                "bulletPoint1": "Erstelle deine eigenen Produkte und Belohnungen",
                "bulletPoint2": "Problemlose Integration mit anderen Mods",
                "bulletPoint3": "Automatische Bezahlung durch Paypal, Stripe oder Paysafecard",
                "bulletPoint5": "Ausführliche Verkaufsstatistiken"
            },
            "andMore": {
                "bulletPoint3": "Ticketsystem",
                "bulletPoint1": "News Seite",
                "bulletPoint4": "Teamseite",
                "description": "VyHub is voll mit weiteren kleinen und großen Funktionen, die für eine großartige Nutzererfahrung sorgen.",
                "bulletPoint2": "Voll funktionale REST API"
            },
            "bansWarnings": {
                "bulletPoint1": "Banne und verwarne Spieler innerhalb der Spiele oder über die Webseite",
                "bulletPoint2": "Integration mit anderen Mods",
                "description": "Verwalte deine Gemeinschaft und setze deine Serverregeln mit unserem Bann- und Verwarnsystem durch."
            }
        },
        "bansWarnings": "Banns & Verwarnungen",
        "viewAllFeatures": "All unsere Funktionen",
        "endcards": {
            "customizable": {
                "bulletPoint3": "Nutze HTML für deine eigenen Unterseiten",
                "bulletPoint4": "Nutze deine eigene (Sub)domain",
                "bulletPoint2": "Passe das Hintergrundbild sowie das Farbschema an",
                "bulletPoint5": "Voll funktionale REST API",
                "bulletPoint1": "Vollkommen anpassbar an deine Bedürfnisse"
            },
            "simple": {
                "bulletPoint2": "Direkter Kontakt zu den Entwicklern für Erweiterungen",
                "bulletPoint3": "Einfach zu nutzende Webseite",
                "bulletPoint1": "Sag auf wiedersehen zu all den nun unnützen Erweiterungen"
            },
            "hasslefree": {
                "bulletPoint1": "Kein eigener Webserver benötigt",
                "bulletPoint2": "Automatische Updates",
                "bulletPoint3": "Keine versteckten Kosten",
                "bulletPoint4": "Schnelle Einrichtung"
            }
        },
        "faq": "Häufig gestellte Fragen",
        "supportedGames": "Unterstütze Spiele / Integrationen",
        "keyFeatures": "Schlüsselfunktionen",
        "features": "Funktionen",
        "hasslefree": "Problemlos",
        "joinOurDiscord": "Tritt unserem Discord bei",
        "customizable": "Anpassbar",
        "pageSubtitle": "Die All-in-One-Management & Monetarisierungsplattform {br}für deine Gaming-Community",
        "contactFormSubtitle": "Hast du Fragen zu Funktionen, Zahlungen oder anderen Dingen? Sende uns eine Nachricht.",
        "announcement": "VyHub ist nun gratis! Schau dir unsere neue Preisseite an.",
        "_communities": {
            "description": "Hunderte von Communities vertrauen VyHub. Werde einer von ihnen!"
        },
        "ourCommunities": "Unsere Communities"
    },
    "_dashboard": {
        "yourInstances": "Deine Instanzen",
        "currentlyProvisioned": "Diese Instanz wird gerade erstellt",
        "instanceDeleted": "Diese Instanz ist gestoppt",
        "detailDialogTitle": "Details",
        "createInstance": "Instanz erstellen",
        "visitInstance": "Besuchen",
        "title": "Dashboard",
        "yourAdminInstances": "Instanzen, auf denen du Admin bist"
    },
    "_instance": {
        "labels": {
            "edit": "Instanz editieren",
            "daysLeft": "Tage übrig",
            "noTimeLeft": "Keine Zeit übrig",
            "extendRuntime": "Laufzeit verlängern",
            "frontendUrl": "FrontEnd URL",
            "cname": "CNAME",
            "apiUrl": "API URL",
            "activePackets": "Aktive Pakete",
            "addAdmin": "Admin hinzufügen",
            "advancedSettings": "Erweiterte Einstellungen",
            "resumeInstance": "Instanz starten",
            "transferOwnership": "Eigentum übertragen",
            "stopInstance": "Instanz stoppen",
            "upgradeVersion": "Version updaten",
            "newExpirationDate": "Neues Ablaufdatum",
            "addons": "Erweiterungen",
            "agreeWithTermsOfServiceAndUpgradeToVersion14": "Ich stimme den AGB zu und führe ein Upgrade auf Version 1.4 durch"
        },
        "instanceName": "Name der Instanz",
        "cnamePointingAt": "CNAME zeigt auf",
        "editInstance": "Instanz editieren",
        "editedInstance": "Instanz erfolgreich editiert",
        "version": "Version",
        "autoUpdate": "Installiere kleinere Updates automatisch",
        "autoUpdateTime": "Zeit des automatischen Updates (UTC)",
        "addedAdmin": "Admin erfolgreich hinzugefügt",
        "_status": {
            "PROVISION": "Frontend einrichten",
            "PROVISIONED": "Bereit",
            "DELETED": "Angehalten",
            "DELETE": "Anhalten",
            "UNPROVISIONED": "API-Server einrichten",
            "REPROVISION": "Wende Änderungen am API Server an"
        },
        "statusHelp": "Kontaktiere den Support, wenn der Status sich nach 10 Minuten nicht ändert.",
        "deletedInstance": "Instanz erfolgreich gestoppt",
        "autoUpdateDescription": "Die Instanz wird zur gewählten Stunde automatisch aktualisiert",
        "autoUpdateActivated": "Automatisches update aktualisiert",
        "removedAdmin": "Admin erfolgreich entfernt",
        "owner": "Besitzer",
        "addAdmin": "Admin hinzufügen",
        "error": {
            "user_not_admin": "Nutzer ist kein Admin",
            "user_not_found": "Nutzer nicht gefunden"
        },
        "statusHelpProvisioned": "Deine Instanz ist bereit zum Nutzen. Wenn die Seite nicht lädt, leere deinen DNS Cache oder starte deinen Router neu. Wenn das Problem noch immer besteht, kontaktiere den Support.",
        "setCNAMEDescription": "Erstelle einen CNAME DNS Eintrag bei deiner Domain mit diesem Ziel. Dieser Eintrag verbindet deine eigene Domain mit dieser VyHub Instanz.",
        "statusHelpProvision": "Wenn der Status sich nicht innerhalb von 5 Minuten ändert, ist der CNAME Eintrag, welcher auf diese Instanz zeigt, wahrscheinlich nicht korrekt gesetzt. Schau in die Dokumentation oder kontaktiere uns, wenn du Hilfe brauchst.",
        "newOwnerDialogDescription": "Gib den Namen der Instanz ein. Du verlierst den Zugriff auf die Instanz, nachdem sie zu einem anderen Nutzer transferiert worden ist.",
        "admins": "Admins",
        "messages": {
            "removedAdmin": "Admin erfolgreich entfernt.",
            "addedAdmin": "Admin erfolgreich hinzugefügt.",
            "instanceReady": "Deine Instanz ist bereit!",
            "doNotOpenBeforeReady": "Öffne die Seite nicht, bevor die Instanz bereit ist!",
            "noActivePackets": "Es gibt keine aktiven Abos für diese Instanz. Stelle sicher, dass du die Instanz vor Ende der Laufzeit verlängerst.",
            "noResourcesAvailable": "Es sind derzeit keine Ressourcen für eine neue Instanz verfügbar. Bitte versuche es später noch einmal.",
            "instanceExtended": "Instanz wurde erfolgreich verlängert"
        },
        "cnameCheckerTool": "CNAME-Überprüfung",
        "extendInstance": "Instanz verlängern",
        "extendInstanceDescription": "Die Laufzeit kann 7 Tage vor Ende der Laufzeit verlängert werden. Wenn die Instanz nicht verlängert wird, wird sie gestoppt.",
        "ownershipTransferSupport": "Bitte kontaktiere den Support, wenn du die Instanz an einen anderen Nutzer übertragen möchtest.",
        "connectOneServer": "Verbinde einen Spielserver",
        "automaticExtension": "Automatische Verlängerung",
        "setUpAutocharge": "Automatische Zahlungen aktivieren",
        "revenueFee": "Einnahmegebühr"
    },
    "log": "Log",
    "_form": {
        "contact": {
            "message": "Nachricht",
            "firstName": "Vorname",
            "email": "Email",
            "subject": "Betreff",
            "lastName": "Nachname",
            "acceptPrivacy": "Ich akzeptiere die Datenschutzerklärung"
        },
        "login": {
            "login": "Einloggen",
            "continue": "Weiter",
            "sendConfirmationCode": "Code senden",
            "registrationRequired": "Registrierung benötigt",
            "register": "Registrieren",
            "email": "Email",
            "emailConfirmation": "Email Bestätigungscode",
            "username": "Nutzername",
            "password": "Passwort",
            "passwordConfirmation": "Passwortbestätigung",
            "error": {
                "password_no_match": "Überprüfe das Passwort bestätigen Feld",
                "username_taken": "Nutzername ist schon vergeben",
                "confirmation_code_no_match": "Überprüfe deinen Email Bestätigungscode",
                "invalid_request": "Ungültiges Passwort",
                "username_not_allowed": "Nutzername nicht erlaubt",
                "email_taken": "Email ist schon vergeben. Bitte logge dich ein.",
                "captcha_low": "Bitte fülle das Captcha aus"
            },
            "forgotPassword": "Passwort vergessen",
            "howDidYouHearAboutUs": "Wie bist du auf uns aufmerksam geworden?",
            "howDidYouHearAboutUsOptions": {
                "searchEngine": "Suchmaschine (Google, Bing, ...)",
                "socialMedia": "Soziale Medien",
                "otherCommunity": "Andere Community",
                "friends": "Freunde",
                "youtube": "Youtube",
                "other": "Andere"
            }
        },
        "validation": {
            "required": "Das Feld wird benötigt",
            "usernameFormat": "Nutzername darf nur die folgenden Zeichen enthalten: a-z, 0-9,.,_,-",
            "usernameLength": "Nutzername muss mindestens 3 Zeichen haben",
            "passwordLength": "Passwort muss mindestens 8 Zeichen haben",
            "emailInvalid": "Email muss gültig sein",
            "passwordNoUppercase": "Passwort muss einen Großbuchstaben enthalten",
            "passwordNoNumber": "Passwort muss eine Zahl enthalten",
            "passwordNoSpecialCharacter": "Passwort muss ein besonderes Zeichen enthalten",
            "passwordMatch": "Passwörter stimmen nicht überein",
            "codeLength": "Code muss 5 Zeichen lang sein",
            "formInvalid": "Formular ist ungültig"
        },
        "submit": "Absenden"
    },
    "_log": {
        "type": {
            "group": "Gruppe",
            "packet": "Paket",
            "news": "News",
            "warning": "Verwarnung",
            "discord": "Discord",
            "instance": "Instanz",
            "server": "Server",
            "system": "System",
            "requirement": "Requirement",
            "design": "Design",
            "user": "Nutzer",
            "ban": "Bann",
            "shop": "Shop"
        },
        "timeAgo": "vor {time}",
        "group_add": "Gruppe hinzugefügt {groupName} {groupId}.",
        "payment_cancelled": "Zahlung abgebrochen. debit_id: {debit_id}.",
        "purchase_revoke": "Kauf widerrufen. Kauf_id: {purchase_id}.",
        "purchase_unrevoke": "Wiederrufener Kauf wieder angewendet. Kauf_id: {purchase_id}.",
        "purchase_refund": "Kauf zurückerstattet. Kauf_id: {purchase_id}, debit_id: {debit_id}, refund_debit_id: {refund_debit_id}.",
        "purchase_finished": "Kauf abgeschlossen. Zahlungs_id: {purchase_id}.",
        "purchase_cancelled": "Kauf abgebrochen. Kauf_id: {purchase_id}.",
        "object_edit": "{classname} mit id {id}: {key} = {value} editiert.",
        "object_delete": "{classname} mit id {id} gelöscht.",
        "object_create": "{classname} mit id {id}: {params} erstellt.",
        "applied_packet_extended": "Laufzeit des angewendeten Pakets {applied_packet_id} verlängert.",
        "applied_packet_not_extended": "Das Verlängern des Pakets {applied_packet_id}: {reason} ist fehlgeschlagen.",
        "edit": "Editiert {name}: {key} = {value}",
        "payment_initiate": "Initiierte {Gateway}-Zahlung. Aktion: {action}, Nachricht: {message}, Code: {status_code}.",
        "payment_process": "Abwicklung des Zahlungsereignisses. Gateway: {Gateway}, Nachricht: {Nachricht}, Detail: {Detail}.",
        "refund_finished": "Rückerstattung abgeschlossen. debit_id: {debit_id}, kauf_id: {purchase_id}.",
        "payment_refund": "{Gateway}-Zahlung zurückerstattet. Aktion: {action}, Nachricht: {message}, Code: {status_code}.",
        "payment_error": "Zahlungsfehler. Gateway: {gateway}, Nachricht: {message}, Aktion: {action}, Detail: {detail}, Code: {status_code}.",
        "debit_status_changed": "Abbuchungsstatus geändert. debit_id: {debit_id}, Status: {alter_Status} -> {neuer_Status}.",
        "autocharge_wrong_account_currency": "Das Konto {account_id} hatte die falsche Währung für die automatische Belastung. Konto: {currency_account}, Kauf: {currency_purchase}",
        "payment_credits_fail": "Kreditzahlung fehlgeschlagen. action: {action}, user_id: {user_id}, debit_id: {debit_id}, credits: {credits}, reason: {reason}.",
        "payment_credits_success": "Kreditauszahlung erfolgreich. action: {action}, user_id: {user_id}, debit_id: {debit_id}, credits: {credits}.",
        "packet_applied": "Angewendetes Paket {packet_title} ({packet_id}) für Benutzer {user_id}. angewandte_paket_id: {angewendete_paket_id}.",
        "payment_event": "Abwicklung des Zahlungsereignisses. Gateway: {Gateway}, Nachricht: {Nachricht}, Detail: {Detail}.",
        "purchase_status_changed": "Kaufstatus geändert. Kauf_ID: {Kauf_ID}, Status: {alter_Status} -> {neuer_Status}.",
        "autocharge_tx_created": "Automatische Belastungstransaktion erstellt. Betrag: {amount}, Lastschrift: {debit_id}, Konto: {account_id}, Benutzer: {user_id}",
        "labels": {
            "level": "Level"
        },
        "messages": {
            "limitReachedFilter": "Protokolllimit erreicht, Filter verwenden."
        }
    },
    "_address": {
        "labels": {
            "city": "Stadt",
            "state": "Staat",
            "selectAddress": "Adresse auswählen",
            "vat_number": "Steueridentifikationsnummer",
            "zip_code": "Postleitzahl",
            "streetAndNumber": "Straße und Hausnummer",
            "addition": "Zusatz",
            "edit": "Adresse bearbeiten",
            "change": "Adresse bearbeiten",
            "add": "Adresse hinzufügen"
        },
        "messages": {
            "changeSuccess": "Händleradresse erfolgreich bearbeitet.",
            "addSuccess": "Neue Adresse erfolgreich erstellt.",
            "selectedSuccess": "Adresse erfolgreich ausgewählt.",
            "noAddressesYet": "Du hast aktuell noch keine Adressen."
        }
    },
    "_errors": {
        "domain_not_available": "Domain nicht verfügbar",
        "wrong_giftcode": "Gutscheincode ist nicht gültig",
        "country_not_allowed": "Käufe aus deinem Land sind nicht möglich.",
        "cart_not_empty": "Dein Warenkorb muss leer sein, um dieses Paket hinzuzufügen.",
        "packet_already_in_cart": "Das Paket ist schon in deinem Warenkorb.",
        "cart_full": "Dein Warenkorb ist voll.",
        "not_found": "Nicht gefunden.",
        "unauthorized": "Du musst eingeloggt sein, um dies zu machen.",
        "coupon": {
            "not_found": "Dieser Code ist ungültig."
        },
        "wrong_currency": "Du kannst keine Pakete mit unterschiedlichen Währungen in deinem Warenkorb haben.",
        "name_not_available": "Name nicht verfügbar",
        "undefined": "Unerwarteter Fehler. Bitte kontaktiere den Support.",
        "packet_not_compatible": "Dieses Paket ist mit einem anderen Paket nicht kompatibel: {packet_title}.",
        "no_server_available": "Keine Server für eine neue Instanz verfügbar. Bitte kontaktiere den Support.",
        "packet_requires_other": "Dieses Paket benötigt ein anderes Paket: {packet_title}.",
        "no_permissions": "Zugriffsfehler: {msg}",
        "packet_not_purchasable": "Du kannst dieses Paket nicht kaufen.",
        "too_many_instances": "Du kannst keine weiteren Instanzen erstellen. Bitte kontaktiere den Support um das Limit zu erhöhen.",
        "missing_properties": "Du hast nicht all benötigten Rechte: {properties}",
        "no_resources_available": "Aktuell gibt es nicht genügend verfügbare Rechenleistung.",
        "packet_relation_violated": "Dieses Paket verletzt eine Paketbeziehung mit einem anderen Paket: {relation_type} {packet_title}."
    },
    "_gateway": {
        "labels": {
            "paypal": "PayPal",
            "stripe": "Stripe",
            "create": "Erstelle eine Zahlungsmethode",
            "edit": "Editiere eine Zahlungsmethode",
            "paysafecard": "Paysafecard",
            "coupon": "Coupon {manuelle Bestätigung}",
            "webhookURL": "Webhook URL"
        },
        "messages": {
            "createSuccess": "Zahlungsmethode wurde erfolgreich erstellt.",
            "deleteSuccess": "Zahlungsmethode erfolreich gelöscht.",
            "editSuccess": "Zahlungsmethode erfolgreich editiert.",
            "formAttributeChangeExplanation": "Die folgenden Attribute werden nicht bearbeitet, wenn kein Wert angegeben wird."
        }
    },
    "_shop": {
        "labels": {
            "cancelPayment": "Zahlung abbrechen",
            "cancelPurchase": "Kauf abbrechen",
            "invoiceLogoURL": "Rechnungslogo URL",
            "cart": "Warenkorb",
            "tax": "Steuer",
            "taxRules": "Steuerregeln",
            "subtotal": "Zwischensumme",
            "checkout": "Bezahlen",
            "payment": "Bezahlung",
            "paymentId": "Zahlungs ID",
            "addToCart": "Zum Einkaufswagen hinzufügen",
            "total": "Gesamt",
            "credits": "Credits",
            "purchaseNow": "Jetzt kaufen",
            "businessAddress": "Firmenadresse",
            "cartTotal": "Warenkorb gesamt",
            "defaultCurrency": "Standardwährung",
            "unfinishedPurchase": "Nicht abgeschlossener Kauf",
            "billingAddress": "Rechnungsadresse",
            "removeAllPackets": "Entferne alle Pakete",
            "donationGoal": "Spendenziel",
            "perMonth": "pro Monat",
            "loginToBuy": "Einloggen um dieses Paket zu kaufen",
            "taxAllowUnknown": "Erlaube Käufe aus Ländern ohne Steuerregel.",
            "taxAllowUnknownDescription": "Wenn deaktiviert, sind Käufe aus Ländern ohne festgelegte expliziete Steuerregel nicht möglich.",
            "invoiceLogoURLDetails": "URL zu dem Logo, welches auf der Rechnung angezeigt wird.",
            "admin": "Shop Administration",
            "orderOverview": "Bestellübersicht",
            "applyCoupon": "Coupon einlösen",
            "couponCode": "Coupon",
            "checkoutCheckboxes": "Checkout-Kontrollkästchen",
            "orderWithObligationToPay": "Zahlungspflichtig bestellen",
            "financeReport": "Finanzbericht",
            "downloadInvoices": "Herunterladen von Rechnungen"
        },
        "messages": {
            "couponsEntered": "Dein coupon wurde erfolgreich gespeichert. Du kannst ihn noch ändern, solange er noch nicht akzeptiert worden ist.",
            "addToCartError": "Ein Fehler ist beim Hinzufügen des Paketes in deinen Warenkorb aufgetreten.",
            "clearCartSuccess": "Alle Pakete wurden aus dem Warenkorb entfernt.",
            "selectGateway": "Bitte wähle deine Zahlungsart.",
            "paymentSuccess": "Die Zahlung wurde erfolgreich abgeschlossen.",
            "paymentPending": "Die Zahlung ist ausstehend. Bitte schließe sie in deinem Warenkorb ab.",
            "unfinishedPurchase": "Es gibt einen offenen Kauf, welcher noch nicht abgeschlossen ist.",
            "confirmCreditsPayment": "Bitte bestätige die Zahlung von {credits} credits.",
            "couponsEditSuccess": "Coupon wurde erfolreich geändert.",
            "notEnoughCredits": "Du hast nicht genügend Credits um die Zahlung abzuschließen. Bitte verwende eine andere Zahlungsmethode oder kaufe mehr Credits.",
            "addToCartSuccess": "Paket wurde erfolreich in den Warenkorb gelegt.",
            "cartEmpty": "Dein Warenkorb ist leer.",
            "mustAgree": "Du musst akzeptieren um fortzufahren!",
            "noAddressSpecified": "Adresse wurde noch nicht angegeben.",
            "removeFromCartSuccess": "Paket wurde erfolgreich aus dem Warenkorb entfernt.",
            "paymentCancelled": "Die Zahlung wurde abgebrochen. Du kannst es im Warenkorb erneut probieren.",
            "purchaseCancelledSuccess": "Der Kauf wurde abgebrochen.",
            "paymentProcessing": "Die Zahlung wurde akzeptiert und wird in Kürze abgeschlossen. Bitte warte ein paar Minuten auf dieser Seite, während die Zahlung abgeschlossen wird.",
            "confirmCouponPayment": "Bitte gib dein {gateway_name} code ein. Die Zahlung wird dann manuell vom Team überprüft.",
            "includesVAT": "Enthält {tax_rate}% Umsatzsteuer.",
            "cancelPurchaseConfirmation": "Laufende Zahlvorgänge werden abgebrochen. Dies kann nicht rückgängig gemacht werden.",
            "couponApplySuccess": "Coupon erfolgreich eingelöst.",
            "selectEmailFirst": "Bitte gebe zuerst eine Email Adresse an",
            "couponRemoveSuccess": "Coupon erfolgreich entfernt.",
            "couponNotApplied": "Der Coupon konnte auf kein Paket im Warenkorb angewendet werden.",
            "selectBillingAddressFirst": "Bitte gebe zuerst eine Rechnungsadresse an.",
            "variablePricePaymentSuccess": "Zahlungsmethode erfolgreich für zukünftige Nutzung erstellt.",
            "startingPaymentFailed": "Es gab einen Fehler beim Starten der Zahlung. Bitte versuche es erneut oder nutze eine andere Zahlungsmethode!",
            "paymentFailed": "Ein Fehler ist während des Zahlvorgangs aufgetreten. Bitte starte den Kauf erneut.",
            "paymentActionFailed": "Beim Weiterleiten auf die Zahlungsseite ist ein Fehler aufgetreten. Bitte versuchen es erneut oder verwende eine andere Zahlungsmethode! Fehlermeldung: {message}",
            "noOngoingPurchase": "Derzeit gibt es keinen laufenden Zahlungsvorgang. Bitte starte diesen im Warenkorb.",
            "notEnoughLiquidityForAddons": "Du brauchst ein positives VyHub-Guthaben oder eine aktivierte automatische Aufladung, um Add-ons zu aktivieren."
        },
        "purchaseStatus": {
            "cancelled": "Abgebrochen",
            "finished": "Abgeschlossen",
            "open": "Offen",
            "refunded": "Zurückerstattet",
            "recurring": "Wiederkehrend",
            "enabled": "Aktiv",
            "disabled": "Abgelaufen",
            "revoked": "Storniert"
        }
    },
    "newInstance": {
        "viewOrder": "Bestellung ansehen",
        "title": "Erstelle eine neue Instanz",
        "operationalTime": "Laufzeit",
        "days": "Tage",
        "prepaid": "Vorauszahlung",
        "additionalPacket": "Erweiterungen",
        "loginRegister": "Einloggen / Registrieren",
        "payment": "Zahlung",
        "recurring": "Wiederkehrend",
        "creditCardButton": "Kredit- oder Debitkarte",
        "currency": "EUR / monat",
        "noAddons": "Keine Erweiterungen verfügbar",
        "domain": "Domain",
        "name": "Name der Instanz",
        "customDomain": "Eigene Domain",
        "customDomainDescription": "Du musst eine Domain besitzen und ein CNAME Eintrag in den DNS Einstellungen deines Registrars setzen. Lies die {docsLink} für mehr Informationen.",
        "domainDescription": "Domain für deine Instanz. Freilassen, wenn du keine eigene Domain ahst.",
        "confirmationDialog": "Die Domain wird unter {domain} erreichbar sein",
        "prepaidDescription": "Immer, wenn die Laufzeit endet, musst du die Laufzeit manuell verlängern."
    },
    "resetPassword": {
        "resetPassword": "Passwort zurücksetzen",
        "backToLogin": "Zurück zum Einloggen",
        "sendLink": "Link senden",
        "sendLinkToEmail": "Wir werden einen Link zum Passwort zurücksetzen senden",
        "emailSent": "Folge den Schritten in der Email, geschickt an {email} (wenn ein dazugehöriger Account existiert)",
        "setPassword": "Passwort setzen",
        "badToken": "Token ist abgelaufen oder ungültig. Bitte fordere einen neuen Token an.",
        "passwordSet": "Erfolg! Du kannst nun dein zum {login_placeholder} nutzen.",
        "login_placeholder": "einloggen",
        "toLogin": "Zum Einloggen",
        "noTokenSpecified": "Kein Token angegeben. Bitte fordere ein neues Token an."
    },
    "_invoice": {
        "invoice": "Rechnung",
        "invoiceDate": "Rechnungsdatum",
        "deliveryDate": "Lieferdatum",
        "paymentMethod": "Zahlungsmethode",
        "transaction": "Transaktion",
        "item": "Artikel",
        "quantity": "Anzahl",
        "price": "Preis",
        "subtotalNoVat": "Zwischensumme (ohne Mehrwertsteuer)",
        "vat": "Mehrwertsteuer",
        "total": "Gesamt",
        "vatNumber": "Steueridentifikationsnummer",
        "refund": "Rückerstattung"
    },
    "_newInstance": {
        "description": "Starte mit deiner eigenen VyHub-Instanz!{br}Keine Zahlungsinformationen erforderlich!{br}{br}Wenn du Fragen haben solltest, lies bitte unsere {documentation}.",
        "prepaidDescription": "Jedes Mal, wenn der Zeitraum endet, musst du manuell für den nächsten Zeitraum vorausbezahlen.",
        "recurringDescription": "VyHub wird vor Ablauf des Zeitraums automatisch verlängert. Die Zahlung erfolgt automatisch. Du kannst bis zu 3 Tage vor Beginn des nächsten Monats kündigen.",
        "title": "Erstelle eine neue Instanz",
        "loginRegister": "Einloggen / Registrieren",
        "currency": "EUR / Monat",
        "name": "Name der Instanz",
        "domainDescription": "Domain für deine Instanz. Freilassen, wenn du keine eigene Domain hast.",
        "customDomain": "Eigene Domain",
        "customDomainDescription": "Du brauchst eine eigene Domain und musst einen CNAME Eintrag in den DNS Einstellungen deines Hosters setzen. Lies die {docsLink} für mehr Informationen.",
        "creditCardButton": "Kredit- oder Kreditkarte",
        "success": "Das Erstellen deiner Instanz kann bis zu 10 Minuten dauern.{br} Gehe zum {dashboard} um den Status zu sehen.",
        "smallCommission": "Kleine <a href='https://docs.vyhub.net/latest/central/account' target='_blank'>Kommission</a> auf deinen Umsatz",
        "noInstancesAvailable": "Aktuell sind keine Instanzen verfügbar. Bitte versuche es später erneut.",
        "instanceNameAndDomain": "Name und Domain"
    },
    "_features": {
        "_shop": {
            "_features": {
                "title5": "Rabatte",
                "text6": "VyHub unterstützt mehrere Zahlungsmethoden. Du kannst PayPal, Paysafecard und Stripe Zahlungen akzeptieren. Mit Stripe werden viele lokale Zahlungsmethoden abgedeckt. Darüber hinaus können Benutzer das eingebaute Kreditsystem für Zahlungen verwenden. Es besteht auch die Möglichkeit, benutzerdefinierte Gutscheincodes für einen Kauf zu akzeptieren, die dann manuell von einem Administrator genehmigt werden müssen.",
                "title4": "Statistiken",
                "headline4": "Statistiken",
                "text4:": "Überwache deine Verkäufe mit den integrierten Statistiken. Zum Beispiel kannst du die Verkäufe pro Monat oder Land filtern.",
                "title2": "Kategorien",
                "headline2": "Unbegrenzte Kategorien",
                "headline5": "Rabatte",
                "title6": "Zahlungsmethoden",
                "headline6": "Zahlungsmethoden",
                "headline1": "Unbegrenzte Pakete",
                "title1": "Pakete",
                "title3": "Prämien",
                "text1": "Pakete sind die Grundlage jedes Webshops. Erstelle deine eigenen Pakete, die du auf der Website für echtes Geld verkaufen kannst. Du kannst Pakete in verschiedenen Kategorien organisieren, um deinen Spielern ein besseres Erlebnis zu bieten. Pakete können Einzelkäufe oder wiederkehrende Zahlungen sein.",
                "text3": "Immer wenn ein Spieler ein Paket kauft, können verschiedene Prämien ausgeführt werden. Prämien können alles sein, von Ingame-Währung bis hin zu Item-Drops. Mit den Prämien kannst du jeden Ingame-Befehl ausführen. Außerdem kannst du Spielern auch Ränge geben!",
                "title7": "PaketErweiterungen",
                "text5": "Du kannst deinen Spielern Rabatte gewähren. Diese Rabatte können für den gesamten Shop oder nur für bestimmte Pakete gelten. Auf diese Weise kannst du Spieler für gute Leistungen belohnen.",
                "headline7": "Paket Erweiterungen",
                "headline3": "Unbegrenzte Prämien",
                "text4": "Überwache deine Verkäufe mit den integrierten Statistiken. Beispielsweise können Verkäufe nach Monat oder nach Land angezeigt werden."
            },
            "title": "Shop",
            "subtitle": "Verkaufe Ränge und Ingame-Gegenstände für echtes Geld."
        },
        "_cutomizability": {
            "_features": {
                "headline2": "Dunkler Modus",
                "text1": "Du kannst das Aussehen deiner Webseite sehr einfach ändern. Das beinhaltet Farben, ein Dunkelmodus oder ein anderes Hintergrundbild.",
                "title2": "DunkelModus",
                "title1": "Theme",
                "headline1": "Ändere das Aussehen",
                "headline4": "Erstelle eigene Seiten",
                "title4": "Erstelle eigene Seiten",
                "headline3": "Bearbeite die Navigationsleiste",
                "text4": "Du kannst eigene Seite mit allen Html und Javascript Möglichkeiten erstellen. Du kannst diese Seiten in der Navigationsleiste anzeigen.",
                "title3": "NavigationsLinks"
            },
            "subtitle": "Passe VyHub deinen Bedürfnissen an.",
            "title": "Anpassbarkeit"
        },
        "_community": {
            "subtitle": "Spare Zeit und Aufwand beim verwalten deiner Community.",
            "_features": {
                "title1": "Banns",
                "title3": "Forum",
                "headline2": "Verwarnungen",
                "title2": "Verwarnungen",
                "headline1": "Banns",
                "text2": "Du kannst Nutzer verwarnen, welche auch nach einer bestimmten Anzahl von Verwarnungen automatisch gebannt werden.",
                "headline3": "Forum",
                "text3": "Deine Spieler können sich in unserem Forum austauschen. Weiterhin ist es möglich, Teameigene Bereiche zu erstellen.",
                "headline4": "Ticket system",
                "text1": "Mit VyHub kannst du Spieler von deinen Gameservern verbannen. Banns können für eine Reihe von Gameservern oder global für alle deine Server erstellt werden. Benutzer haben die Möglichkeit, einen Bann-Protest zu erstellen, der dann von den Admins eingesehen werden kann.",
                "text5": "Gruppen können Teil des Teams sein. Es wird automatisch eine Teamseite erstellt, die es den Spielern ermöglicht, die richtige Person zu finden.",
                "text4": "Um deine Community besser zu verwalten und den Supportprozess zu vereinfachen, bietet VyHub ein Ticketsystem. Spieler können Tickets erstellen, die dann von Teammitgliedern gelöst werden.",
                "title6": "Anzeigen",
                "title4": "Ticket-System",
                "title5": "Teamseite",
                "headline5": "Teamseite",
                "headline6": "Anzeigen",
                "text6": "Wiederkehrende Anzeigen sind kleine Nachrichten, die periodisch auf den Gameservern angekündigt werden können.",
                "title7": "Neuigkeiten",
                "headline7": "Neuigkeiten",
                "text7": "Auf der Hauptseite können Nachrichten erstellt und angezeigt werden. So kannst du deine Spieler auf dem Laufenden halten. Darüber hinaus gibt die News-Seite einen Überblick über alle Ihre Server, neuen Spieler und Shop-Ziele."
            },
            "title": "Community"
        },
        "_furtherFeatures": {
            "_features": {
                "title1": "SSL",
                "headline2": "Mehrsprachige Unterstützung",
                "headline3": "Voll funktionsfähige API",
                "text3": "VyHub kommt mit einer voll funktionsfähigen REST-API. Du kannst diese API verwenden, um alles (und mehr) zu tun, was du auch mit dem Frontend machen könntest. Auch eigene Plugins, die die API integrieren, sind möglich.",
                "text4": "VyHub kommt mit einer kostenlosen Subdomain vyhub.app. Wenn du lieber deine eigene Adresse verwenden möchtest, ist dies kostenlos möglich!",
                "title3": "Voll funktionsfähige API",
                "title4": "Eigene Webseitenadresse verwenden",
                "headline4": "Optional: Verwende eine eigene Webseitenadresse",
                "headline1": "Gratis SSL Zertifikat",
                "title2": "Sprachen",
                "text2": "Um VyHub besser zu personalisieren und mit deiner Community zu interagieren, ist VyHub in mehrere Sprachen übersetzt. Derzeit werden drei Sprachen vollständig unterstützt, weitere Sprachen werden derzeit übersetzt! VyHub Nutzer wie du können bei der Übersetzung helfen."
            },
            "subtitle": "Es gibt noch viel mehr zu entdecken.",
            "title": "Weitere Funktionen"
        },
        "_dashboard": {
            "_features": {
                "title2": "Server-Dashboard",
                "headline1": "Spieler-Dashboard",
                "title3": "SpielerStatistiken",
                "title1": "Dashboard",
                "text1": "Über das Spieler-Dashboard kannst du alle wichtigen Informationen auf einen Blick sehen. Dies schließt alle verbundenen Konten des Spielers ein. Außerdem werden Statistiken auf dem Dashboard angezeigt. Standardmäßig wird die Spielzeit aufgezeichnet, es können jedoch noch weitere Statistiken angezeigt werden!",
                "headline3": "Spielerstatistiken",
                "headline2": "Server-Dashboard",
                "text2": "Sieh dir alle Online-Spieler mit dem Server-Dashboard an. Über dieses Dashboard kannst du von einem Ort aus auf alle wichtigen spieler- und spielbezogenen Funktionen zugreifen.",
                "title4": "Spielergruppen",
                "headline4": "Spielergruppen"
            },
            "title": "Dashboard",
            "subtitle": "Alle Spielerinformationen auf einen Blick."
        },
        "_groupsAndTeams": {
            "_features": {
                "headline2": "Belohne Spieler mit Gruppen",
                "title1": "Gruppen",
                "headline1": "Erstelle eigene Gruppen",
                "title3": "Berechtigungssystem",
                "headline3": "Berechtigungssystem",
                "text1": "Gruppen sind die Grundlage des in VyHub implementierten Berechtigungssystems. Jeder Spieler kann einer oder mehreren Gruppen angehören. Die Gruppen können unterschiedliche Berechtigungen haben. Gruppen können auch nach einem Kauf vergeben werden.",
                "title2": "BelohneSpieler",
                "text3": "Alle Funktionen auf der Website werden durch Berechtigungen geschützt. Jede Gruppe, die du erstellst, kann unterschiedliche Berechtigungen haben. Dadurch ist es möglich, eine Hierarchie von Gruppen zu erstellen. Dies kann vollständig an deine Anforderungen angepasst werden, um beispielsweise Gruppen für Teammitglieder zu erstellen.",
                "title4": "Berechtigungsstufen",
                "headline4": "Berechtigungsstufen"
            },
            "subtitle": "Du kannst Gruppen und Berechtigungen einfach verwalten.",
            "title": "Gruppen und Teams"
        },
        "allFeatures": "Alle Funktionen"
    },
    "_games": {
        "_features": {
            "gmodIngameDashboard": "Ingame-Dashboard für Banns und Verwarnungen",
            "bans": "Banns und zeitliche-Banns",
            "gmodPlayerSync": "Spielergruppen synchronisieren (Unterstützung für ULX, xAdmin, SAM, FAdmin, ServerGuard und mehr)",
            "minecraftPlayerSync": "Spielergruppen synchronisieren (Unterstützung für LuckPerms)",
            "playtimeStatistic": "Spielzeitstatistik für jeden Spieler",
            "discordPlayerSync": "Benutzerrollen synchronisieren",
            "periodicAdverts": "Regelmäßige Nachrichten",
            "reservedSlots": "Reservierte Slots",
            "warnings": "Verwarnungen",
            "rewards": "Unendliche Möglichkeiten mit Prämien (benutzerdefinierte Befehle/Skripte, Ingame-Geld, Item-Drops...)",
            "playerSync": "Benutzerrollen synchronisieren",
            "discordNotifications": "Anpassbare Verbots-/Warnungs-/Kaufbenachrichtigungen in Textkanälen"
        },
        "minecraftDescription": "VyHub unterstützt Minecraft, das meistgespielte überlebens-Sandbox-Spiel. Derzeit erfordert dieses Plugin Java >= 17 und Minecraft >= 1.13.",
        "discordDescription": "VyHub unterstützt Discord, die kostenlose Sprach-, Video- und Text-Chat-App.",
        "gmodDescription": "VyHub unterstützt Garry's Mod, der bekannte Physikbaukasten.",
        "teamspeakDescription": "VyHub unterstützt TeamSpeak, den Voice-Chat, bei dem du die volle Kontrolle hast.",
        "supportedMods": "Unterstütze Mods"
    },
    "amount": "Betrag",
    "country": "Land",
    "_payInstance": {
        "labels": {
            "title": "Instanz bezahlen"
        }
    },
    "_purchases": {
        "labels": {
            "unrevoke": "Unwiederrufen",
            "decline": "Ablehnen",
            "confirm": "Bestätigen",
            "allPurchases": "Alle Käufe",
            "myPurchases": "Meine Käufe",
            "appliedPackets": "Angewandte Pakete",
            "revoke": "Widerrufen",
            "creditsSpent": "Credits ausgegeben",
            "details": "Kaufdetails",
            "salesCount": "Anzahl an Käufen",
            "totalRevenue": "Gesamter Umsatz",
            "monthlyRevenue": "Monatlicher Umsatz",
            "revoked": "Widerrufen",
            "refund": "Erstatten",
            "refunded": "Erstattet",
            "amountNet": "Netto-Betrag",
            "amountTotal": "Gesamtbetrag",
            "confirmDebitText": "Kauf bestätigen? Dies kann nicht rückgängig gemacht werden.",
            "confirmPurchases": "Käufe bestätigen",
            "editAppliedPacket": "Angewandtes Paket editieren",
            "cancelSubscription": "Abonnement kündigen",
            "addAppliedPacket": "Angewandtes Paket hinzufügen",
            "declineDebitText": "Kauf abbrechen? Dies kann nicht rückgängig gemacht werden.",
            "revenueByCountry": "Umsatz nach Land",
            "paymentGateway": "Zahlungsmethode",
            "coupon": "Coupon",
            "showApprovedDebits": "Genehmigte Abbuchungen anzeigen",
            "addAppliedReward": "Angewendete Prämie hinzufügen",
            "reward": "Prämie"
        },
        "messages": {
            "refundInitSuccess": "Erstattung erfolgreich gestartet.",
            "refreshSuccess": "Zahlungsdetails erfolgreich geupdated.",
            "revokeSuccess": "Kauf erfolgreich zurückgezogen.",
            "unrevokeSuccess": "Kauf erfolgreich wieder angewandt.",
            "editAppliedPacketSuccess": "Angewandtes Paket erfolgreich bearbeitet.",
            "deleteAppliedPacketSuccess": "Angewandtes Paket erfolgreich gelöscht.",
            "createAppliedPacketSuccess": "Angewandtes Paket erfolgreich erstellt.",
            "refundConfirm": "Bist du dir sicher, dass du den Kauf zurückerstatten möchtest?",
            "cancelSubscriptionConfirm": "Bist du dir sicher, dass du das Abo kündigen möchtest?",
            "confirmPurchaseSuccess": "Kauf erfolgreich bestätigt",
            "declinePurchaseSuccess": "Kauf erfolgreich abgebrochen",
            "cancelSubscriptionSuccess": "Abonnement erfolgreich gekündigt."
        }
    },
    "extend": "Verlängern",
    "next": "Nächster Schritt",
    "unexpectedError": "Unerwarter Fehler",
    "login": "Login",
    "confirm": "Confirm",
    "_partners": {
        "title": "Partner",
        "headline": "Bist du bereit, dass Beste Spielserververwaltungssystem zu bewerben?",
        "lifetimeCustomerValue": "Lebenslanger Kundenwert",
        "comingSoon": "Erscheint bald",
        "description2": "Dein VyHub.net Nutzerkonto enthält bereits einen Link zum Teilen",
        "description1": "Deine Freunde und Follower werden es dir danken, wenn sie VyHub zum ersten Mal ausprobieren.{br} Du bekommst außerdem eine wiederkehrende Provision von 25%.",
        "grabAffiliateLink": "Hol deinen Link"
    },
    "back": "Zurück",
    "shop": "Shop",
    "actions": "Aktionen",
    "_pricing": {
        "vyhubCloud": "VyHub Cloud",
        "feature1": "Gehostete Webseite",
        "feature2": "Anpassbarer Webshop",
        "feature3": "Unbegrenzte Pakete",
        "feature4": "Subdomain enthalten",
        "feature5": "Eigene Domain möglich",
        "feature6": "Aktualisierungen enthalten",
        "allFeatures": "Alle kostenlosen Funktionen",
        "hosted": "Selbst gehostet",
        "feature7": "Kostenloses SSL-Zertifikat",
        "q2": "Gibt es eine kostenlose Testversion?",
        "a2": "Ja! Da wir keinen monatlichen Preis berechnen, kannst du VyHub komplett kostenlos nutzen und testen.",
        "startNow": "Starte jetzt",
        "smallCommission": "Kleine Provision auf deinen Umsatz",
        "a1": "VyHub kann kostenlos verwendet werden. Du kannst es so lange verwenden, wie du magst. Wir berechnen nur eine kleine Provision auf deinen monatlichen Umsatz. Du zahlst also nur, wenn du Geld verdienst. Weitere Einzelheiten zu den Gebühren findest du in unserer <a target=\"_blank\" href=\"https://docs.vyhub.net/latest/central/account\">Dokumentation</a>.",
        "a3": "Da es kein Abonnement gibt, musst du nichts kündigen.",
        "a4": "Bitte kontaktiere unser Vertriebsteam unter <a href=\"mailto:info@vyhub.net\">info@vyhub.net</a> mit einer kurzen Beschreibung deiner Community und deinen Anforderungen. Wir werden uns so schnell wie möglich bei dir melden.",
        "noMonthlySubscription": "Kein monatliches Abonnement",
        "q1": "Was kostet VyHub? Ist es wirklich kostenlos?",
        "feature8": "Unterstützt mehrere Gameserver",
        "shFeature1": "Einfache Einrichtung via Docker",
        "shFeature2": "Selbst gehostetes Front- und Backend",
        "shFeature3": "Alle VyHub-Funktionen",
        "shFeature4": "Premium-Erweiterungen enthalten",
        "shFeature6": "Vollständiger Datenbankzugriff",
        "shFeature5": "Aktualisierungen enthalten",
        "revenue/Month": "Umsatz / Monat",
        "fact1": "Du zahlst nur, wenn du mit VyHub Geld verdienst",
        "fact2": "Je mehr du verdienst, desto mehr sparst du an Gebühren",
        "fact3": "Sonderkonditionen für große Spieleserver verfügbar",
        "q3": "Kann ich jederzeit kündigen?",
        "q4": "Gibt es Rabatte für größere Spieleserver?",
        "addons": {
            "communication": "Kommunikations Add-on"
        },
        "commission": "Kommission",
        "formulaForFeeCalculation": "Formel zur Berechnung der Gebühren"
    },
    "register": "Registrieren",
    "date": "Datum",
    "gateway": "Gateway",
    "invoice": "Rechnung",
    "firstName": "Vorname",
    "purchases": "Käufe",
    "lastName": "Nachname",
    "subject": "Überschrift",
    "settings": "Einstellungen",
    "documentation": "Dokumentation",
    "congratulations": "Glückwunsch!",
    "contact": "Kontakt",
    "_cart": {
        "labels": {
            "add": "Zum Warenkorb hinzufügen"
        }
    },
    "_affiliate": {
        "payouts": "Auszahlungen",
        "payout": "Auszahlung",
        "payoutNow": "Jetzt Auszahlen",
        "totalReferrals": "Geworbene Nutzer",
        "registeredUsers": "Registrierte Nutzer",
        "amount": "Betrag",
        "paypalEmail": "Paypal E-Mail",
        "processedOn": "Bearbeitet am",
        "transactionId": "Transaktionsadresse",
        "messages": {
            "linkCopied": "Link in die Zwischenablage kopiert.",
            "payoutSuccess": "Zahlung erfolgreich intiiert."
        },
        "status": {
            "rejected": "Abgelehnt",
            "finished": "Abgeschlossen",
            "created": "Erstellt",
            "pending": "Ausstehend"
        },
        "yourAffiliateLink": "Dein Partnerlink",
        "currentBalance": "Aktuelles Guthaben",
        "pendingBalance": "Ausstehendes Guthaben",
        "totalPaid": "Auszahlung Gesamt",
        "affiliateResources": "Affiliate-Ressourcen",
        "recipient": "Empfänger",
        "iban": "IBAN",
        "currentBalanceDescription": "Zur Auszahlung verfügbares Guthaben.",
        "pendingBalanceDescription": "Unbezahlte Gebühren der Nutzer (Bearbeitung kann bis zu 4 Wochen dauern).",
        "affiliateDashboard": "Partner Dashboard",
        "overlayDescription": "Dieses Dashboard ist für die Benutzer des Partnerprogramms. Suchst du dein VyHub Konto?",
        "lookHere": "Schau hier.",
        "minimumPayout5€": "Minimale Auszahlung von 5€"
    },
    "message": "Nachricht",
    "acceptPrivacy": "Ich akzeptiere die Datenschutzerklärung",
    "submit": "Absenden",
    "create": "Erstellen",
    "areYouSure": "Bist du dir sicher?",
    "username": "Nutzername",
    "email": "Email",
    "password": "Passwort",
    "activeUntil": "Aktiv bis",
    "price": "Preis",
    "summary": "Zusammenfassung",
    "description": "Beschreibung",
    "instance": "Instanz",
    "search": "Suchen",
    "owner": "Besitzer",
    "admins": "Admins",
    "admin": "Admin",
    "status": "Status",
    "error": "Fehler",
    "version": "Version",
    "support": "Support",
    "close": "Schließen",
    "dashboard": "Dashboard",
    "packets": "Pakete",
    "packet": "Paket",
    "edit": "Bearbeiten",
    "contactUs": "Kontaktiere uns",
    "user": "Nutzer",
    "continue": "Weiter",
    "every": "Jede",
    "cart": "Warenkorb",
    "id": "ID",
    "instances": "Instanzen",
    "transactions": "Transaktionen",
    "noEntries": "Keine Einträge.",
    "enable": "Aktivieren",
    "users": "Nutzer",
    "_addon": {
        "addon": "Erweiterung",
        "messages": {
            "addonEdited": "Erweiterung erfolgreich bearbeitet.",
            "addonApplied": "Erweiterung erfolgreich hinzugefügt.",
            "addonCancelled": "Erweiterung erfolgreich gekündigt."
        },
        "addons": "Erweiterungen",
        "newAddon": "Neue Erweiterung",
        "editAddon": "Erweiterung bearbeiten",
        "noAddonsAvailable": "Keine Erweiterungen verfügbar",
        "currentAddons": "Aktuelle Erweiterungen",
        "cancelAddonDescription": "Bist du dir sicher, dass du die Erweiterung deaktivieren möchtest? Die Erweiterung wird zum Ende der aktuellen Laufzeit gekündigt und deaktiviert.",
        "expiresOn": "Läuft ab"
    },
    "delete": "Löschen",
    "_account": {
        "labels": {
            "chargeAccount": "Account aufladen",
            "chargeOn": "am",
            "balance": "Kontostand",
            "autocharge_enabled": "Automatisches Aufladen aktiviert",
            "autocharge_disabled": "Automatisches Aufladen deaktiviert",
            "autocharge": "Automatisches Aufladen",
            "enableAutocharge": "Automatisches Aufladen aktivieren",
            "nextCharge": "Nächste Zahlung"
        },
        "messages": {
            "autocharge": "Wenn Auto-Charge aktiviert ist, wird dein negativer Kontostand nach Monatsende automatisch von deiner hinterlegten Zahlungsmethode abgebucht. Es gilt ein Mindestbetrag von 5 EUR pro Zahlung.",
            "noChargeScheduled": "Derzeit ist keine Zahlung geplant. Bitte schaue zu Beginn des nächsten Monats noch einmal vorbei.",
            "cancelConfirm": "Sind Sie sicher, dass Sie die automatische Kontoaufladung abbrechen möchten?"
        }
    },
    "domain": "Domain",
    "add": "Hinzufügen",
    "cancel": "Abbrechen",
    "select": "Auswählen",
    "name": "Name",
    "_support": {
        "messages": {
            "needHelp": "Du brauchst Hilfe? Erstelle ein Ticket.",
            "requestSendSuccess": "Ticket erfolgreich abgeschickt. Du solltest zeitnah eine Bestätigungsmail erhalten."
        }
    },
    "payments": "Zahlungen",
    "success": "Erfolg",
    "loginRegister": "Anmelden / Registrieren",
    "subscribe": "Abonnieren",
    "_legal": {
        "messages": {
            "dataCorrect": "Hiermit versichere ich, dass die angegebenen Daten (insbesondere Rechnungsadresse) wahrheitsgemäß und vollständig sind.",
            "agreeToS": "Ich stimme den Nutzungsbedingungen zu.",
            "noWithdraw": "Ich fordere und stimme ausdrücklich zu, dass die Matbye UG bereits vor Ablauf der Widerrufsfrist mit der Ausführung der erworbenen Leistung beginnt. Ferner ist mir bekannt, dass ich das mir gesetzlich zustehende Widerrufsrecht bereits mit vollständiger Vertragserfüllung durch die Matbyte UG verliere.",
            "agreeTo": "Ich stimme den {tos} zu.",
            "tos": "Nutzungsbedingungen"
        },
        "cookieTitle": "🍪 Datenschutzeinstellungen",
        "cookieDescription": "Wir verwenden Cookies 🍪, um dein Surferlebnis auf unserer Website zu verbessern, unseren Website-Traffic zu analysieren und zu verstehen, woher unsere Besucher kommen. Weitere Informationen dazu findest du in unserer {privacyPolicy}.",
        "privacyPolicyPage": "Datenschutzerklärung",
        "necessaryCookies": "Notwendige Cookies",
        "preferences": "Einstellungen",
        "acceptSelected": "Ausgewählte akzeptieren",
        "cookiePreferenceDescription": "Hier kannst du deine Cookie-Einstellungen manuell anpassen."
    },
    "revenue": "Umsatz",
    "partners": "Partner",
    "docs": "Dokumente",
    "shopAdministration": "Shop-Verwaltung",
    "checkout": "Kasse",
    "toggle": "Umschalten",
    "addVersion": "Version hinzufügen",
    "availableInstances": "Verfügbare Instanzen",
    "save": "Speichern",
    "created": "Erstellt",
    "_newsletter": {
        "thankYou": "Danke für die Registrierung!"
    },
    "giftCodes": "Geschenkcodes",
    "authorizeApplication": "Applikation autorisieren",
    "details": "Einzelheiten",
    "account": "Konto",
    "comingSoon": "Demnächst",
    "_statistic": {
        "instanceStatistics": "Instanzstatistiken",
        "interval": {
            "DAILY": "Täglich",
            "WEEKLY": "Wöchentlich",
            "MONTHLY": "Monatlich",
            "YEARLY": "Jährlich"
        }
    },
    "accept": "Akzeptieren",
    "copy": "Kopieren",
    "enter": "Eintreten",
    "disabled": "Deaktivieren",
    "end": "Beenden",
    "labels": "Label",
    "category": "Kategorie",
    "start": "Start",
    "filter": "Filter",
    "_shopFeatures": {
        "title": "Shop Funktionen",
        "allShopFeatures": "Alle Shopfunktionen",
        "packets": {
            "description": "VyHub bietet die Möglichkeit, Pakete auf deinem Gameserver zu verkaufen. Pakete können in Kategorien und Unterkategorien organisiert werden. Es ist möglich, Paket-Upgrade-Pfade und Pakete mit spezieller Verfügbarkeit zu erstellen. Das kann verwendet werden, um Pakete nur an Spieler zu verkaufen, die einen bestimmten Rang, eine bestimmte Spielzeit, oder ein bestimmtes Paket besitzen.",
            "bp1": "Unbegrenzte Pakete",
            "bp2": "Unbegrenzte Kategorien",
            "bp3": "Unbegrenzte Unterkategorien",
            "bp4": "Für einen Freund kaufen",
            "bp6": "Kaufe Pakete mit credits",
            "bp5": "Pakete mit einstellbarem Preis",
            "bp7": "Pakete mit Upgrades",
            "bp8": "Bedingte Pakete"
        },
        "rewards": {
            "description": "Immer wenn ein Spieler ein Paket über VyHub kauft, erhält er automatisch die zugewiesenen Belohnungen. Eine Belohnung kann ein beliebiges Ingame-Kommando oder eine Gruppenmitgliedschaft sein.",
            "bp1": "Automatische Prämienabwicklung nach dem Kauf",
            "bp2": "Prämienborlagen, welche verwendet werden können",
            "bp3": "Mehrere Prämien pro Paket",
            "bp4": "VIP-Ränge",
            "bp5": "Gegenstände im Spiel",
            "bp6": "Zugriff auf reservierte Slots"
        },
        "discounts": {
            "description": "VyHub bietet eine große Auswahl an Rabattoptionen für den Shop. Spielerabhängige Rabatte sind möglich. Beispielsweise kannst du Spielern einen Rabatt gewähren, die einen bestimmten Rang oder eine bestimmte Spielzeit haben.",
            "bp1": "Prozentuale Rabatte",
            "bp2": "Maximale Nutzung des Rabattes",
            "bp3": "Maximale Nutzung des Rabattes pro Spieler",
            "bp4": "Rabatte für bestimmte Spieler",
            "bp5": "Bedingte Rabatte"
        },
        "statistics": {
            "description": "VyHub bietet eine breite Palette an Statistiken, die dir helfen, den Überblick über deine Verkäufe zu behalten. Du kannst nach Kategorien sortieren, wie viele Pakete du verkauft hast, wie hoch der durchschnittliche Kaufbetrag ist oder wie viel Geld du verdient hast. Viele weitere Statistiken stehen im Dashboard zur Verfügung. Alle Statistiken werden übersichtlich und leicht verständlich dargestellt.",
            "bp1": "Umfangreiche Verkaufsstatistiken",
            "bp2": "Gesamtumsatz",
            "bp4": "Verkäufe nach Kategorie",
            "bp3": "Durchschnittlicher Kaufbetrag"
        },
        "payments": {
            "description": "VyHub bietet eine nahtlose Zahlungsabwicklung für deine Gaming-Community. Mit der Unterstützung von über 20 Zahlungsmethoden über PayPal, Stripe und Paysafecard geben wir deinen Spielern die Flexibilität, die bevorzugte Zahlmethode zu wählen. Du musst einfach ein Konto bei einem der Zahlungsgateways wie PayPal, Stripe oder Paysafecard erstellen. Alle Zahlungen werden über diese abgewickelt. Das bedeutet, dass von unserer Seite keine weiteren Verzögerungen der Auszahlung oder Auszahlungsgebühren anfallen. Du hast sofort Zugriff auf das Geld.",
            "bp1": "Über 20 Zahlungsmethoden",
            "bp2": "Es ist lediglich ein Paypal-/Stripe-/Paysafecard-Konto erforderlich",
            "bp3": "Akzeptiere alle Geschenkkarten-ähnlichen Methoden durch manuelle Verarbeitung",
            "bp4": "Keine Auszahlungsverzögerungen",
            "bp5": "Keine Auszahlungsgebühren"
        }
    },
    "reset": "Zurücksetzen",
    "versions": "Versionen",
    "rewards": "Prämien",
    "discounts": "Rabatte",
    "statistics": "Statistiken",
    "andMuchMore": "Und viel mehr...",
    "_loginRegister": {
        "alreadyHaveAccount": "Du hast schon ein Konto?",
        "welcome": "Willkommen!",
        "noAccount": "Du hast noch kein Konto?",
        "welcomeBack": "Willkommen zurück!",
        "helpDescription": "Brauchst du Hilfe? Du kannst uns über die folgenden Kanäle erreichen."
    },
    "paymentProcessing": "Zahlungsabwicklung",
    "logout": "Ausloggen"
}
