{
    "_footer": {
        "_help": {
            "status": "Статус-сторінка",
            "support": "Підтримка",
            "docs": "Документація"
        },
        "_legal": {
            "privacyPolicy": "Політика конфіденційності",
            "termsOfService": "Умови використання",
            "about": "Інформація"
        },
        "about": "Про VyHub",
        "help": "Отримати допомогу",
        "company": "Компанія",
        "legal": "Юридичні питання",
        "_about": {
            "supportedGames": "Ігри, які підтримуються",
            "pricing": "Ціни",
            "blog": "Блог",
            "demo": "Демо",
            "features": "Параметри"
        },
        "_company": {
            "partners": "Партнери",
            "affiliateProgram": "Партнерська програма"
        }
    },
    "_invoice": {
        "subtotalNoVat": "Проміжний підсумок (без ПДВ)",
        "invoice": "Рахунок",
        "invoiceDate": "Дата рахунку",
        "deliveryDate": "Дата доставки",
        "vatNumber": "Номер платника ПДВ",
        "paymentMethod": "Метод оплати",
        "transaction": "Транзакція",
        "quantity": "Кількість",
        "price": "Ціна",
        "vat": "ПДВ",
        "total": "Всього",
        "item": "Предмет"
    },
    "_home": {
        "sections": {
            "shop": {
                "description": "Створіть власний інтернет-магазин і монетизуйте свій ігровий сервер за допомогою нашої просунутої, але простої у використанні системи магазинів.",
                "bulletPoint3": "Автоматична обробка платежів (PayPal, Stripe, Paysafecard)",
                "bulletPoint4": "Спеціальні пропозиції, коди знижок та багато іншого",
                "bulletPoint5": "Повна статистика продажів",
                "bulletPoint1": "Створіть власні продукти та винагороди",
                "bulletPoint2": "Легка інтеграція з іншими модами"
            },
            "bansWarnings": {
                "bulletPoint2": "Інтеграція з іншими модами",
                "description": "Керуйте своєю спільнотою та забезпечуйте дотримання правил на сервері за допомогою нашої комплексної системи заборон та попереджень.",
                "bulletPoint1": "Банити та попереджати гравців у грі або через веб-панель"
            },
            "andMore": {
                "bulletPoint1": "Сторінка новин",
                "description": "У VyHub є безліч маленьких і великих додаткових функцій, які забезпечують чудовий досвід взаємодії користувачів.",
                "bulletPoint2": "Повнофункціональний REST API",
                "bulletPoint4": "Сторінка команди"
            }
        },
        "endcards": {
            "simple": {
                "bulletPoint1": "Попрощайтеся з усіма видами непотрібних плагінів",
                "bulletPoint2": "Прямий контакт з розробниками для покращень",
                "bulletPoint3": "Проста у використанні веб-панель"
            },
            "customizable": {
                "bulletPoint1": "Повністю регульована та налаштована під ваші потреби",
                "bulletPoint2": "Налаштувати фонове зображення та схему кольорів",
                "bulletPoint3": "Завантажити html щоб створити власні субсторінки",
                "bulletPoint5": "Повнофункціональний REST API",
                "bulletPoint4": "Використовуйте власний (суб)домен"
            },
            "hasslefree": {
                "bulletPoint1": "Не потрібен власний веб-простір",
                "bulletPoint2": "Автоматичні оновлення",
                "bulletPoint3": "Без прихованих витрат",
                "bulletPoint4": "Швидке налаштування"
            }
        },
        "_faq": {
            "answer1": "VyHub - це більше, ніж просто інтернет-магазин. Це комплексна система управління спільнотою, що пропонує такі важливі функції, як заборони та попередження.",
            "answer2": "Встановлення та використання VyHub є безкоштовним. Ми стягуємо лише невелику комісію з вашого щомісячного доходу. Таким чином, ви платите тільки тоді, коли заробляєте гроші.",
            "answer4": "Так, ви можете використовувати існуючий домен, створивши запис CNAME, який вказуватиме на ваш екземпляр VyHub.",
            "question5": "Я користувач GExtension. Чи можу я перенести свої дані на VyHub?",
            "question6": "Де можна отримати допомогу?",
            "answer5": "Так, ви можете легко <a target=\"_blank\" href=\"https://docs.vyhub.net/latest/guide/import/gextension/\">імпортувати</a>свої дані.<br/><br/>",
            "answer6": "Будь ласка, спочатку ознайомтеся з нашою <a target=\"_blank\" href=\"https://docs.vyhub.net\">документацією</a>, щоб отримати відповіді на технічні питання. Ви можете зв'язатися з нами за допомогою контактної форми нижче.",
            "question1": "Що відрізняє VyHub від наших конкурентів?",
            "question2": "Скільки коштує VyHub?",
            "answer3": "Так! Оскільки ми не беремо щомісячної плати, ви можете використовувати та тестувати VyHub абсолютно безкоштовно.",
            "question4": "Чи можу я використовувати власний домен?",
            "question3": "Чи надаєте ви безкоштовну пробну версію?"
        },
        "pageSubtitle": "Універсальна платформа управління та монетизації {br}для вашої ігрової спільноти",
        "rightManagement": "Контроль доступу",
        "bansWarnings": "Бани та попередження",
        "ourGoals": "Наші цілі",
        "andMore": "І багато іншого...",
        "supportedGames": "Підтримувані ігри / Інтеграції",
        "ourAmbitions": "Наші прагнення",
        "shop": "Магазин",
        "discordIntegration": "Інтеграція Discord",
        "joinOurDiscord": "Приєднуйтесь до нашого Discord",
        "keyFeatures": "Ключові параметри",
        "simple": "Просто",
        "customizable": "Налаштовується",
        "hasslefree": "Простота і зручність",
        "faq": "Поширені запитання",
        "viewAllFeatures": "Переглянути всі параметри",
        "features": "Параметри",
        "announcement": "VyHub тепер безкоштовний! Ознайомтеся з нашими цінами.",
        "contactFormSubtitle": "У вас є питання щодо функціоналу, оплати або чогось іншого? Напишіть нам повідомлення."
    },
    "_newInstance": {
        "customDomainDescription": "Вам потрібно володіти доменом і створити запис CNAME у налаштуваннях DNS вашого реєстратора домену. Прочитайте {docsLink} для отримання додаткової інформації.",
        "success": "Створення вашого екземпляра може зайняти до 10 хвилин.{br}Перейдіть на {dashboard}, щоб переглянути статус.",
        "creditCardButton": "Кредитна або дебетова картка",
        "name": "Назва екземпляра",
        "domainDescription": "Домен для вашого екземпляра. Залиште порожнім, якщо у вас його немає.",
        "customDomain": "Власний домен",
        "loginRegister": "Вхід / Реєстрація",
        "recurringDescription": "VyHub продовжується автоматично до закінчення терміну дії. Оплата здійснюється автоматично. Ви можете скасувати за 3 дні до початку наступного місяця.",
        "prepaidDescription": "Кожного разу, коли закінчується період дії VyHub, ви повинні вручну внести передоплату за наступний період.",
        "currency": "EUR / місяць",
        "title": "Створити новий екземпляр",
        "description": "Почніть роботу з власним екземпляром VyHub!{br}Платіжна інформація не потрібна!{br}{br}Якщо у вас виникли запитання, будь ласка, прочитайте нашу {documentation}."
    },
    "_instance": {
        "labels": {
            "agreeWithTermsOfServiceAndUpgradeToVersion14": "Погодьтеся з Умовами надання послуг та оновіть до версії 1.4",
            "edit": "Редагувати екземпляр",
            "daysLeft": "залишилось днів",
            "newExpirationDate": "Новий термін придатності",
            "noTimeLeft": "Часу не залишилось",
            "upgradeVersion": "Оновити версію",
            "addons": "Аддони",
            "cname": "CNAME",
            "apiUrl": "API URL",
            "activePackets": "Активні пакети",
            "addAdmin": "Додати адміна",
            "advancedSettings": "Додаткові налаштування",
            "stopInstance": "Зупинити екземпляр",
            "resumeInstance": "Відновити екземпляр",
            "transferOwnership": "Передати право власності"
        },
        "setCNAMEDescription": "Створіть CNAME DNS-запис для вашого власного домену з цією метою. Це скерує ваш власний домен до цього екземпляра VyHub.",
        "statusHelpProvision": "Якщо цей статус не зміниться протягом 5 хвилин, можливо, запис CNAME для вашого власного домену налаштовано неправильно. Перевірте документацію або зверніться до служби підтримки, якщо вам потрібна допомога.",
        "autoUpdate": "Автоматично встановлювати виправлення, що не порушують роботу системи",
        "autoUpdateDescription": "Екземпляр автоматично оновлюється в заданий час UTC",
        "autoUpdateActivated": "Автоматичне оновлення активовано",
        "extendInstance": "Продовжити екземпляр",
        "extendInstanceDescription": "Час роботи вашого екземпляра можна продовжити за 7 днів до завершення. Якщо екземпляр не буде продовжено вчасно, його буде зупинено.",
        "ownershipTransferSupport": "Якщо ви хочете передати право власності на ваш екземпляр іншому користувачеві, зверніться до служби підтримки.",
        "automaticExtension": "Автоматичне продовження",
        "cnamePointingAt": "CNAME вказує на",
        "statusHelp": "Зверніться до служби підтримки, якщо статус не зміниться через 10 хвилин.",
        "statusHelpProvisioned": "Ваш екземпляр готовий до використання. Якщо сайт не завантажується, спробуйте очистити кеш DNS або перезавантажити роутер. Якщо це не вирішило проблему, зверніться до служби підтримки.",
        "editInstance": "Редагувати екземпляр",
        "editedInstance": "Екземпляр успішно відредаговано",
        "deletedInstance": "Екземпляр успішно видалено",
        "version": "Версія",
        "autoUpdateTime": "Час автоматичного оновлення (UTC)"
    },
    "_header": {
        "labels": {
            "register": "Зареєструватися",
            "login": "Вхід",
            "logout": "Вихід"
        },
        "start": "Старт",
        "games": "Ігри",
        "pricing": "Ціни",
        "partners": "Партнери",
        "blog": "Блог",
        "demo": "Демо",
        "dashboard": "Інформаційна панель",
        "contact": "Контакти",
        "faq": "FAQ",
        "docs": "Документи",
        "admin": "Адмін",
        "profile": "Профіль",
        "affiliate": "Партнерство",
        "purchases": "Покупки",
        "features": "Параметри"
    },
    "_dashboard": {
        "title": "Інформаційна панель",
        "yourInstances": "Ваші Екземпляри",
        "visitInstance": "Відвідати",
        "createInstance": "Створити екземпляр",
        "detailDialogTitle": "Деталі",
        "currentlyProvisioned": "Цей екземпляр наразі створюється",
        "instanceDeleted": "Цей екземпляр зупинено"
    },
    "log": {
        "labels": {
            "log": "Лог"
        }
    },
    "unexpectedError": "Неочікувана помилка",
    "country": "Країна",
    "add": "Додати",
    "cancel": "Скасувати",
    "price": "Ціна",
    "details": "Деталі",
    "status": "Статус",
    "error": "Помилка",
    "close": "Закрити",
    "packets": "Пакети",
    "packet": "Пакет",
    "id": "ID",
    "continue": "Продовжити",
    "every": "Кожний",
    "_form": {
        "login": {
            "login": "Вхід",
            "register": "Зареєструватися",
            "email": "Email",
            "username": "Ім'я користувача",
            "continue": "Продовжити"
        },
        "contact": {
            "email": "Email",
            "subject": "Тема",
            "message": "Повідомлення"
        },
        "submit": "Надіслати"
    },
    "_shop": {
        "labels": {
            "cart": "Кошик",
            "invoiceLogoURL": "URL логотипу рахунку",
            "invoiceLogoURLDetails": "URL логотипу, який відображається в рахунку.",
            "admin": "Управління магазином",
            "applyCoupon": "Застосувати купон",
            "couponCode": "Код купона",
            "tax": "Податок",
            "taxRules": "Правила оподаткування",
            "subtotal": "Проміжний підсумок",
            "checkout": "Оформити замовлення",
            "payment": "Оплата",
            "paymentId": "ID платежу",
            "addToCart": "Додати в кошик",
            "total": "Всього",
            "businessAddress": "Юридична адреса",
            "credits": "Кредити",
            "purchaseNow": "Купити зараз",
            "orderOverview": "Огляд замовлень",
            "cartTotal": "Всього в кошику",
            "defaultCurrency": "Валюта за замовчуванням",
            "unfinishedPurchase": "Незавершена покупка",
            "billingAddress": "Адреса для виставлення рахунку",
            "removeAllPackets": "Видалити всі пакети",
            "perMonth": "в місяць",
            "loginToBuy": "Увійдіть, щоб придбати цей пакет",
            "checkoutCheckboxes": "Встановіть прапорці для оформлення замовлення",
            "taxAllowUnknown": "Дозволити покупки з країн без податкового правила.",
            "taxAllowUnknownDescription": "Якщо цю функцію вимкнено, покупки з країн, для яких не налаштовано чітке податкове правило, будуть неможливими.",
            "cancelPayment": "Скасувати платіж",
            "cancelPurchase": "Скасувати покупку"
        },
        "messages": {
            "confirmCreditsPayment": "Будь ласка, підтвердіть сплату {credits} кредитів.",
            "confirmCouponPayment": "Будь ласка, введіть код {gateway_name}. Після цього платіж буде вручну схвалений членом команди.",
            "couponsEntered": "Ваш купон успішно додано. Ви можете редагувати свій купон, поки ваша покупка не буде підтверджена.",
            "couponsEditSuccess": "Купон успішно відредаговано.",
            "notEnoughCredits": "У вас недостатньо кредитів для оплати цієї покупки. Будь ласка, оберіть інший спосіб оплати або придбайте більше кредитів.",
            "addToCartError": "Виникла помилка при додаванні пакета до кошика.",
            "addToCartSuccess": "Пакет успішно додано до кошика.",
            "cartEmpty": "Ваш кошик порожній.",
            "mustAgree": "Ви повинні погодитися, щоб продовжити!",
            "startingPaymentFailed": "Під час ініціювання платежу виникла помилка. Будь ласка, спробуйте ще раз або скористайтеся іншим способом оплати!",
            "paymentActionFailed": "Виникла помилка при перенаправленні на сторінку оплати. Будь ласка, спробуйте ще раз або скористайтеся іншим способом оплати! Повідомлення про помилку: {message}",
            "selectGateway": "Будь ласка, оберіть спосіб оплати.",
            "noOngoingPurchase": "Наразі немає поточної покупки. Будь ласка, почніть оформлення замовлення в кошику.",
            "noAddressSpecified": "Адреса ще не вказана.",
            "removeFromCartSuccess": "Пакет успішно видалено з кошика.",
            "clearCartSuccess": "Успішно видалено всі пакети з кошика.",
            "paymentCancelled": "Цей платіж було скасовано. Ви можете спробувати ще раз, зайшовши до кошика.",
            "paymentProcessing": "Платіж був схвалений і буде завершений найближчим часом. Будь ласка, зачекайте кілька хвилин на цій сторінці, поки ваш платіж обробляється.",
            "paymentFailed": "Під час оплати виникла помилка. Будь ласка, спробуйте перезапустити процес.",
            "paymentPending": "Цей платіж очікує на розгляд. Будь ласка, завершіть його, відвідавши кошик.",
            "unfinishedPurchase": "Наразі триває купівля, яка ще не завершена.",
            "purchaseCancelledSuccess": "Покупка скасована.",
            "couponApplySuccess": "Купон успішно використано.",
            "couponRemoveSuccess": "Купон успішно видалено.",
            "couponNotApplied": "Купон не може бути застосований до жодного пакету у вашому кошику.",
            "includesVAT": "Включає {tax_rate}% ПДВ.",
            "selectBillingAddressFirst": "Будь ласка, спочатку оберіть адресу для виставлення рахунку.",
            "selectEmailFirst": "Будь ласка, спочатку оновіть свою електронну адресу",
            "cancelPurchaseConfirmation": "Розпочаті платежі скасовуються. Всі введені купони втрачаються. Скасування покупки не може бути відмінено."
        },
        "purchaseStatus": {
            "cancelled": "Скасовано",
            "finished": "Завершено",
            "refunded": "Відшкодовано",
            "recurring": "Повторення",
            "enabled": "Активно",
            "disabled": "Прострочено",
            "revoked": "Відкликано",
            "open": "Відкрити"
        }
    },
    "_log": {
        "type": {
            "system": "Система",
            "user": "Користувач",
            "ban": "Бан",
            "shop": "Магазин",
            "group": "Група",
            "news": "Новини",
            "requirement": "Вимоги",
            "design": "Дизайн",
            "warning": "Попередження",
            "discord": "Discord",
            "server": "Сервер",
            "packet": "Пакет"
        },
        "edit": "Відредаговано {name}: {key} = {value}",
        "object_edit": "Відредаговано {classname} з id {id}: {key} = {value}.",
        "object_delete": "Видалено {classname} з id {id}.",
        "object_create": "Створено {classname} з id {id}: {params}",
        "applied_packet_extended": "Застосований пакет {applied_packet_id} продовжено.",
        "applied_packet_not_extended": "Не вдалося продовжити застосований пакет {applied_packet_id}: {reason}.",
        "group_add": "Додано групу {groupName} {groupId}.",
        "refund_finished": "Відшкодування завершено. дебет_id: {debit_id}, покупка_id: {purchase_id}.",
        "payment_initiate": "Ініційовано платіж {gateway}. дія: {action}, повідомлення: {message}, Код: {status_code}.",
        "payment_refund": "Повернуто платіж {gateway}. дія: {action}, повідомлення: {message}, Код: {status_code}.",
        "payment_cancelled": "Платіж скасовано. дебет_id: {debit_id}.",
        "packet_applied": "Застосовано пакет {packet_title} ({packet_id}) для користувача {user_id}. застосовано_пакет_id: {applied_packet_id}.",
        "payment_event": "Обробка платіжної операції. шлюз: {gateway}, повідомлення: {message}, деталі: {detail}.",
        "payment_process": "Здійснено процес оплати. шлюз: {gateway}, повідомлення: {message}, дія: {action}, деталі: {detail}.",
        "payment_error": "Помилка платежу. шлюз: {gateway}, повідомлення: {message}, дія: {action}, деталі: {detail}, код: {status_code}.",
        "debit_status_changed": "Змінено дебетовий статус. дебет_id: {debit_id}, статус: {old_status} -> {new_status}.",
        "purchase_status_changed": "Змінено статус покупки. покупка_id: {purchase_id}, статус: {old_status} -> {new_status}.",
        "purchase_finished": "Покупку завершено. покупка_id: {purchase_id}.",
        "purchase_cancelled": "Покупку скасовано. покупка_id: {purchase_id}.",
        "purchase_revoke": "Покупку відкликано. покупка_id: {purchase_id}.",
        "purchase_unrevoke": "Покупка не відкликана. покупка_id: {purchase_id}.",
        "purchase_refund": "Покупку відшкодовано. покупка_id: {purchase_id}, дебет_id: {debit_id}, повернення_дебету_id: {refund_debit_id}.",
        "timeAgo": "{time} тому",
        "payment_credits_success": "Оплата кредиту успішна. дія: {action}, користувач_id: {user_id}, дебет_id: {debit_id}, кредити: {credits}.",
        "payment_credits_fail": "Не вдалося оплатити кредит. дія: {action}, користувач_id: {user_id}, дебет_id: {debit_id}, кредити: {credits}, причина: {reason}."
    },
    "_address": {
        "labels": {
            "city": "Місто",
            "state": "Штат",
            "zip_code": "Поштовий код",
            "vat_number": "Номер платника ПДВ",
            "selectAddress": "Виберіть адресу",
            "add": "Додати адресу",
            "change": "Змінити адресу",
            "streetAndNumber": "Вулиця та номер будинку",
            "addition": "Доповнення"
        },
        "messages": {
            "changeSuccess": "Юридична адреса була успішно змінена.",
            "addSuccess": "Нова адреса успішно додана.",
            "selectedSuccess": "Адреса успішно обрана.",
            "noAddressesYet": "Ви ще не маєте жодної адреси."
        }
    },
    "_errors": {
        "packet_requires_other": "Цьому пакету потрібен інший пакет: {packet_title}.",
        "packet_not_compatible": "Цей пакет не сумісний з іншими пакетами: {packet_title}.",
        "packet_relation_violated": "Цей пакет порушує зв'язок пакета з іншим пакетом: {relation_type} {packet_title}.",
        "packet_already_in_cart": "Цей пакет вже у вашому кошику.",
        "packet_not_purchasable": "Ви не можете придбати цей пакет.",
        "cart_full": "Ваш кошик заповнений.",
        "missing_properties": "Ви не маєте всіх необхідних параметрів: {properties}",
        "no_permissions": "Помилка доступу: {msg}",
        "unauthorized": "Ви повинні увійти в систему, щоб зробити це.",
        "wrong_currency": "У вашому кошику не може бути пакетів з різними валютами.",
        "coupon": {
            "not_found": "Цей код неправильний."
        },
        "country_not_allowed": "Покупки з вашої країни заборонені.",
        "cart_not_empty": "Щоб додати цей пакет, ваш кошик має бути порожнім.",
        "not_found": "Не знайдено."
    },
    "_gateway": {
        "labels": {
            "paypal": "PayPal",
            "stripe": "Stripe",
            "create": "Створити платіжний шлюз",
            "edit": "Редагувати платіжний шлюз",
            "paysafecard": "Paysafecard",
            "coupon": "Купон (підтвердження в ручному режимі)",
            "webhookURL": "URL-адреса веб-хука"
        },
        "messages": {
            "createSuccess": "Платіжний шлюз успішно створено.",
            "deleteSuccess": "Платіжний шлюз успішно видалено.",
            "editSuccess": "Платіжний шлюз успішно відредаговано.",
            "formAttributeChangeExplanation": "Атрибути вказані нижче не будуть редагуватися, якщо не вказано жодного значення."
        }
    },
    "_cart": {
        "labels": {
            "add": "Додати в кошик"
        }
    },
    "_purchases": {
        "labels": {
            "myPurchases": "Мої покупки",
            "allPurchases": "Всі покупки",
            "appliedPackets": "Застосовані пакети",
            "revoke": "Відкликати",
            "revoked": "Відкликано",
            "unrevoke": "Скасувати відкликання",
            "refund": "Повернення коштів",
            "refunded": "Відшкодовано",
            "amountNet": "Сума нетто",
            "amountTotal": "Загальна сума",
            "details": "Деталі покупки",
            "salesCount": "Кількість продажів",
            "totalRevenue": "Загальний дохід",
            "monthlyRevenue": "Щомісячний дохід",
            "creditsSpent": "Витрачені кредити",
            "revenueByCountry": "Дохід за країнами",
            "editAppliedPacket": "Редагування застосованого пакету",
            "cancelSubscription": "Скасувати підписку",
            "addAppliedPacket": "Додати застосований пакет",
            "confirmPurchases": "Підтвердити покупку",
            "coupon": "Купон",
            "confirm": "Підтвердити",
            "decline": "Зниження",
            "confirmDebitText": "Підтвердити покупку? Це не можна скасувати.",
            "declineDebitText": "Скасувати покупку? Це не можна скасувати.",
            "showApprovedDebits": "Показати підтверджені платежі",
            "paymentGateway": "Платіжний шлюз",
            "addAppliedReward": "Додати застосовану винагороду",
            "reward": "Винагорода"
        },
        "messages": {
            "cancelSubscriptionSuccess": "Підписку успішно скасовано.",
            "refundInitSuccess": "Повернення коштів успішно ініційовано.",
            "editAppliedPacketSuccess": "Застосований пакет успішно відредаговано.",
            "deleteAppliedPacketSuccess": "Застосований пакет успішно видалено.",
            "cancelSubscriptionConfirm": "Ви впевнені, що хочете скасувати цю підписку?",
            "confirmPurchaseSuccess": "Покупку успішно схвалено",
            "declinePurchaseSuccess": "Покупку успішно скасовано",
            "revokeSuccess": "Покупку успішно скасовано.",
            "refreshSuccess": "Платіжні дані успішно оновлено.",
            "unrevokeSuccess": "Покупку успішно скасовано.",
            "createAppliedPacketSuccess": "Застосований пакет успішно створено.",
            "refundConfirm": "Ви впевнені, що хочете повернути кошти за цю покупку?"
        }
    },
    "_affiliate": {
        "status": {
            "finished": "Завершено",
            "created": "Створено"
        }
    },
    "_features": {
        "_shop": {
            "title": "Магазин",
            "_features": {
                "title1": "Пакети",
                "title2": "Категорії",
                "title3": "Винагороди",
                "title4": "Статистика",
                "headline4": "Статистика",
                "title5": "Знижки",
                "headline5": "Знижки",
                "title6": "Платіжні шлюзи"
            }
        },
        "_cutomizability": {
            "_features": {
                "title1": "Тема"
            }
        },
        "_community": {
            "_features": {
                "title1": "Бани",
                "headline1": "Бани",
                "title2": "Попередження",
                "headline2": "Попередження",
                "title3": "Форум",
                "headline3": "Форум",
                "title6": "Оголошення",
                "headline6": "Оголошення"
            }
        },
        "_dashboard": {
            "title": "Панель",
            "_features": {
                "title2": "Серверна панель",
                "title1": "Панель"
            }
        },
        "_groupsAndTeams": {
            "_features": {
                "title1": "Групи"
            }
        }
    },
    "areYouSure": "Ви впевнені?",
    "delete": "Видалити",
    "shop": "Магазин",
    "register": "Зареєструватися",
    "date": "Дата",
    "gateway": "Шлюз",
    "amount": "Сума",
    "invoice": "Рахунок",
    "payments": "Платежі",
    "purchases": "Покупки",
    "subject": "Тема",
    "message": "Повідомлення",
    "submit": "Надіслати",
    "settings": "Налаштування",
    "create": "Створити",
    "login": "Вхід",
    "confirm": "Підтвердити",
    "select": "Вибрати",
    "name": "Ім'я",
    "summary": "Підсумок",
    "description": "Опис",
    "search": "Пошук",
    "admin": "Адмін",
    "dashboard": "Панель",
    "documentation": "Документація",
    "edit": "Редагувати",
    "cart": "Кошик",
    "_games": {
        "_features": {
            "warnings": "Попередження"
        }
    },
    "username": "Ім'я користувача",
    "email": "E-Mail",
    "enable": "Увімкнути",
    "actions": "Дії",
    "created": "Створено",
    "end": "Кінець",
    "disabled": "Відключено",
    "shopAdministration": "Управління магазином",
    "checkout": "Оформити замовлення",
    "save": "Зберегти",
    "revenue": "Прибуток"
}
